{
    "//comment": "these settings can be overwritten in your settings.json file, see ro_rando.py for how the config files are merged",

    "danger": {
        "city_distance": 1000,
        "max_city_mult": 5,
        "dungeon_mult": 3
    },
    "location_anchors": [
        { "map": "prontera", "x": 0, "y": 0 },
        { "map": "ayothaya", "x": 1600, "y": 1800},
        { "map": "moscovia", "x": 1800, "y": -2100},
        { "map": "morocc", "x": -1700, "y": -1700}
    ],
    "ignore_maps": [
        "prt_fild08a", "prt_fild08b", "prt_fild08c", "prt_fild08d",
        "prt_church", "prt_cas", "prt_gld", "prt_cas_q",
        "izlude_a", "izlude_b", "izlude_c", "izlude_d",
        "nif_fild01", "nif_fild02",
        "yggdrasil01"
    ]
}
